just_rag/__init__.py
just_rag/base_rag.py
just_rag/citation.py
just_rag/cited_classic_rag.py
just_rag/classic_rag.py
just_rag/document_loader/universal_loader/__init__.py
just_rag/document_loader/universal_loader/loader.py
just_rag/document_loader/universal_loader/markdown_loader.py
just_rag/document_loader/universal_loader/pdf_loader.py
just_rag/document_loader/universal_loader/universal_document_loader.py
just_rag/document_loader/universal_loader/unstructured_file_loader.py
just_rag/document_loader/universal_loader/website_loader.py
just_rag/llm_factory.py
just_rag/self_rag/__init__.py
just_rag/self_rag/decision_generate.py
just_rag/self_rag/decision_has_hallucination.py
just_rag/self_rag/decision_retry.py
just_rag/self_rag/graph_builder.py
just_rag/self_rag/graph_state.py
just_rag/self_rag/node_generate.py
just_rag/self_rag/node_grade_documents.py
just_rag/self_rag/node_increase_retry.py
just_rag/self_rag/node_retreiver.py
just_rag/self_rag/node_transform_query.py
just_rag/utils/format_document.py
just_rag/vector_store/base_vector_store_builder.py
just_rag/vector_store/just_chroma_vector_store_builder.py
just_rag-0.3.0.dist-info/METADATA
just_rag-0.3.0.dist-info/WHEEL
just_rag-0.3.0.dist-info/RECORD
