Metadata-Version: 2.1
Name: just-rag
Version: 0.3.0
Summary: Just do RAG without pain.
License: MIT
Author: Samuel
Author-email: samuelint@gmail.com
Requires-Python: >=3.10,<=3.12.4
Classifier: License :: OSI Approved :: MIT License
Classifier: Programming Language :: Python :: 3
Classifier: Programming Language :: Python :: 3.10
Classifier: Programming Language :: Python :: 3.11
Classifier: Programming Language :: Python :: 3.12
Provides-Extra: universal-loader
Requires-Dist: chromadb (>=0.5.4,<0.6.0)
Requires-Dist: langchain (>=0.2.7,<0.3.0)
Requires-Dist: langchain-anthropic (>=0.1.20,<0.2.0)
Requires-Dist: langchain-community (>=0.2.7,<0.3.0)
Requires-Dist: langchain-huggingface (>=0.0.3,<0.0.4)
Requires-Dist: langchain-openai (>=0.1.16,<0.2.0)
Requires-Dist: langgraph (>=0.1.8,<0.2.0)
Requires-Dist: markdown (>=3.6,<4.0) ; extra == "universal-loader"
Requires-Dist: pydantic-settings (>=2.3.4,<3.0.0)
Requires-Dist: pypdf (>=4.3.0,<5.0.0) ; extra == "universal-loader"
Requires-Dist: unstructured (>=0.14.10,<0.15.0) ; extra == "universal-loader"
